graphysio/__init__.py
graphysio/__main__.py
graphysio/dialogs.py
graphysio/legend.py
graphysio/main.py
graphysio/mainui.py
graphysio/structures.py
graphysio/utils.py
graphysio/algorithms/__init__.py
graphysio/algorithms/filters.py
graphysio/algorithms/waveform.py
graphysio/plotwidgets/__init__.py
graphysio/plotwidgets/curves.py
graphysio/plotwidgets/plotwidget.py
graphysio/plotwidgets/poiselector.py
graphysio/plotwidgets/puplot.py
graphysio/plotwidgets/spectrogram.py
graphysio/plotwidgets/tsplot.py
graphysio/readdata/__init__.py
graphysio/readdata/baseclass.py
graphysio/readdata/csv.py
graphysio/readdata/dwc.py
graphysio/readdata/edf.py
graphysio/readdata/excel.py
graphysio/readdata/parquet.py
graphysio/transformations/__init__.py
graphysio/transformations/feet_time_interval.py
graphysio/transformations/feet_to_curve.py
graphysio/transformations/perfusion_index.py
graphysio/transformations/precise_feet.py
graphysio/transformations/pulse_transit.py
graphysio/ui/__init__.py
graphysio/ui/convert_ui_to_py.sh
graphysio/ui/csvrequest.py
graphysio/ui/csvrequest.ui
graphysio/ui/curveproperties.py
graphysio/ui/curveproperties.ui
graphysio/ui/curveselect.py
graphysio/ui/curveselect.ui
graphysio/ui/cycledetect.py
graphysio/ui/cycledetect.ui
graphysio/ui/datetime.py
graphysio/ui/datetime.ui
graphysio/ui/dwcopen.py
graphysio/ui/dwcopen.ui
graphysio/ui/filter.py
graphysio/ui/filter.ui
graphysio/ui/loopwidget.py
graphysio/ui/loopwidget.ui
graphysio/ui/mainwindow.py
graphysio/ui/mainwindow.ui
graphysio/ui/periodexport.py
graphysio/ui/periodexport.ui
graphysio/ui/poiwidget.py
graphysio/ui/poiwidget.ui
graphysio/ui/setuppuloop.py
graphysio/ui/setuppuloop.ui
graphysio/writedata/__init__.py
graphysio/writedata/csv.py
graphysio/writedata/ecgplot.py
graphysio/writedata/edf.py
graphysio/writedata/exporter.py
graphysio/writedata/matlab.py
graphysio/writedata/parquet.py
graphysio-2025.9.20.dist-info/METADATA
graphysio-2025.9.20.dist-info/WHEEL
graphysio-2025.9.20.dist-info/entry_points.txt
graphysio-2025.9.20.dist-info/licenses/LICENSE
graphysio-2025.9.20.dist-info/RECORD
