Metadata-Version: 2.4
Name: graphysio
Version: 2025.9.20
Summary: Visualizer and analyser for biometric signals
Project-URL: Repository, https://github.com/jaj42/GraPhysio
Author-email: Jona Joachim <jona@joachim.cc>
License-Expression: ISC
License-File: LICENSE
Requires-Python: <=3.14,>=3.10
Requires-Dist: ecg-plot<0.3,>=0.2.8
Requires-Dist: matplotlib<4,>=3.10.0
Requires-Dist: numexpr~=2.10
Requires-Dist: pandas<3,>=2
Requires-Dist: pathvalidate<4,>=3
Requires-Dist: pebble<6,>=5.0.7
Requires-Dist: physiocurve>=2024.12.16
Requires-Dist: pint<0.26,>=0.24
Requires-Dist: pyqtgraph<0.14,>=0.13
Requires-Dist: pyside6~=6.8
Requires-Dist: scipy~=1.15
Provides-Extra: all
Requires-Dist: dwclib[dwcmeta]>=2025.3.12; extra == 'all'
Requires-Dist: pyarrow>=14; extra == 'all'
Requires-Dist: pyedflib>=0.1.38; extra == 'all'
Requires-Dist: pyshortcuts~=1.9; extra == 'all'
Provides-Extra: dwc
Requires-Dist: dwclib[dwcmeta]>=2025.3.12; extra == 'dwc'
Provides-Extra: edf
Requires-Dist: pyedflib>=0.1.38; extra == 'edf'
Provides-Extra: excel
Requires-Dist: python-calamine<0.4,>=0.3.1; extra == 'excel'
Provides-Extra: parquet
Requires-Dist: pyarrow>=14; extra == 'parquet'
Provides-Extra: shortcuts
Requires-Dist: pyshortcuts~=1.9; extra == 'shortcuts'
